CHANGES.txt
LICENSE.txt
MANIFEST.in
setup.cfg
setup.py
melody_dl/InfoExtractor.py
melody_dl/MelodyDL.py
melody_dl/__init__.py
melody_dl/cli.py
melody_dl/utils.py
melody_dl.egg-info/PKG-INFO
melody_dl.egg-info/SOURCES.txt
melody_dl.egg-info/dependency_links.txt
melody_dl.egg-info/requires.txt
melody_dl.egg-info/top_level.txt