Metadata-Version: 1.1
Name: melody-dl
Version: 0.1.5
Summary: Command line utility that downloads audio files from various websites.
Home-page: http://melody-dl.com
Author: Simon W. Jackson | miniArray
Author-email: simon@miniarray.com
License: LICENSE.txt
Download-URL: https://github.com/miniarray/melody-dl/tarball/v0.1.5
Keywords: download,music,audio
Platform: UNKNOWN
